directory/__init__.py
directory/exceptions.py
directory/helpers.py
directory/models.py
directory/scraper.py
directory/search.py
middlebury_directory-1.0.0.dist-info/DESCRIPTION.rst
middlebury_directory-1.0.0.dist-info/METADATA
middlebury_directory-1.0.0.dist-info/RECORD
middlebury_directory-1.0.0.dist-info/WHEEL
middlebury_directory-1.0.0.dist-info/metadata.json
middlebury_directory-1.0.0.dist-info/top_level.txt
