Metadata-Version: 2.0
Name: middlebury-directory
Version: 1.0.0
Summary: A Python API for the Middlebury directory.
Home-page: https://github.com/coursereviews/directory
Author: Dana Silver
Author-email: dsilver@middlebury.edu
License: MIT
Keywords: directory middlebury search people
Platform: UNKNOWN
Classifier: Intended Audience :: Developers
Classifier: License :: OSI Approved :: MIT License
Classifier: Operating System :: OS Independent
Classifier: Programming Language :: Python
Classifier: Programming Language :: Python :: 2
Classifier: Programming Language :: Python :: 2.7
Classifier: Programming Language :: Python :: 3
Classifier: Programming Language :: Python :: 3.5
Classifier: Topic :: Internet :: WWW/HTTP
Classifier: Topic :: Internet :: WWW/HTTP :: Dynamic Content
Requires-Dist: cssselect
Requires-Dist: lxml
Requires-Dist: requests
